messytables_jts.py
setup.py
bin/csv2jts
messytables_jts.egg-info/PKG-INFO
messytables_jts.egg-info/SOURCES.txt
messytables_jts.egg-info/dependency_links.txt
messytables_jts.egg-info/requires.txt
messytables_jts.egg-info/top_level.txt