Metadata-Version: 1.0
Name: messytables-jts
Version: 0.3
Summary: Python library for mapping Messytable cell types to strings
Home-page: UNKNOWN
Author: Martin Keegan
Author-email: martin.keegan@okfn.org
License: Apache Licence v2.0
Platform: UNKNOWN
